{"@type": "/osmosis.gamm.v1beta1.Pool", "address": "osmo195vm9cpsdntewfe7l83yx2w28hkfvx33lyu454gvfrr6f5m7gcas420nk8", "id": "732", "poolParams": {"swapFee": "2000000000000000", "exitFee": "0"}, "futurePoolGovernor": "24h", "totalShares": {"denom": "gamm/pool/732", "amount": "104310392488958921255"}, "poolAssets": [{"token": {"denom": "ibc/F16FDC11A7662B86BC0B9CE61871CBACF7C20606F95E86260FD38915184B75B4", "amount": "295943871171370700660185"}, "weight": "536870912000000"}, {"token": {"denom": "uosmo", "amount": "17506475385"}, "weight": "536870912000000"}], "totalWeight": "1073741824000000"}